examples/__init__.py
examples/benchmark.py
examples/cpu_kernels.py
examples/cuda_kernels.py
examples/full_analysis.py
examples/histos.py
examples/simple_hzz.py
examples/timing.py
examples/train_dnn.py
hepaccelerate/__init__.py
hepaccelerate/__version__.py
hepaccelerate/backend_cpu.py
hepaccelerate/backend_cuda.py
hepaccelerate/core.py
hepaccelerate/utils.py
hepaccelerate-0.2.3.dist-info/METADATA
hepaccelerate-0.2.3.dist-info/RECORD
hepaccelerate-0.2.3.dist-info/WHEEL
hepaccelerate-0.2.3.dist-info/top_level.txt
