Metadata-Version: 2.1
Name: hepaccelerate
Version: 0.2.3
Summary: Fast kernels for analyzing jagged columnar data common in high-energy physics.
Home-page: https://github.com/hepaccelerate/hepaccelerate
Author: Joosep Pata
Author-email: joosep.pata@cern.ch
License: BSD
Platform: UNKNOWN
Classifier: License :: OSI Approved :: BSD License
Classifier: Programming Language :: Python
Classifier: Programming Language :: Python :: 3
Classifier: Programming Language :: Python :: 3.6
Classifier: Programming Language :: Python :: Implementation :: CPython
Requires-Python: >=3.6.0
Provides-Extra: dask
Provides-Extra: cuda
Requires-Dist: uproot
Requires-Dist: awkward
Requires-Dist: numba
Requires-Dist: xxhash
Requires-Dist: lz4
Requires-Dist: requests
Provides-Extra: cuda
Requires-Dist: cupy; extra == 'cuda'
Requires-Dist: cudatoolkit; extra == 'cuda'
Provides-Extra: dask
Requires-Dist: dask; extra == 'dask'
Requires-Dist: distributed; extra == 'dask'
